content_hub-0.2.0.dist-info/licenses/LICENSE
contentctl/__init__.py
contentctl/__main__.py
contentctl/config/__init__.py
contentctl/config/loader.py
contentctl/config/resolver.py
contentctl/config/selectors.py
contentctl/execute/__init__.py
contentctl/execute/sync.py
contentctl/gateway/__init__.py
contentctl/gateway/defaults.py
contentctl/gateway/parser.py
contentctl/operation_kit/__init__.py
contentctl/operation_kit/sync.py
contentctl/operations/__init__.py
contentctl/operations/adopt.py
contentctl/operations/deploy.py
contentctl/operations/init.py
contentctl/plan/__init__.py
contentctl/plan/sync.py
contentctl/schema/__init__.py
contentctl/schema/content-hub.schema.json
contentctl/utils/__init__.py
contentctl/utils/concurrent.py
contentctl/utils/streams.py
content_hub-0.2.0.dist-info/METADATA
content_hub-0.2.0.dist-info/WHEEL
content_hub-0.2.0.dist-info/entry_points.txt
content_hub-0.2.0.dist-info/top_level.txt
content_hub-0.2.0.dist-info/RECORD
