Metadata-Version: 2.4
Name: content-hub
Version: 0.2.0
Summary: A CLI for managing the lifecycle of directory content across multiple locations.
Author: iplaylf2
License-Expression: BSD-3-Clause
Project-URL: Homepage, https://github.com/iplaylf2/content-hub
Project-URL: Issues, https://github.com/iplaylf2/content-hub/issues
Project-URL: Source, https://github.com/iplaylf2/content-hub
Keywords: cli,directory,workspace,lifecycle,sync,contentctl
Classifier: Development Status :: 4 - Beta
Classifier: Environment :: Console
Classifier: Intended Audience :: Developers
Classifier: Programming Language :: Python :: 3
Classifier: Programming Language :: Python :: 3.14
Classifier: Topic :: Utilities
Classifier: Topic :: System :: Filesystems
Classifier: Operating System :: OS Independent
Requires-Python: >=3.14
License-File: LICENSE
Requires-Dist: jsonschema>=4.26.0
Requires-Dist: pyyaml>=6.0.3
Dynamic: license-file
